custom_virtualenv.py
custom_virtualenv-3.0.0.dist-info/LICENSE
custom_virtualenv-3.0.0.dist-info/METADATA
custom_virtualenv-3.0.0.dist-info/WHEEL
custom_virtualenv-3.0.0.dist-info/entry_points.txt
custom_virtualenv-3.0.0.dist-info/top_level.txt
custom_virtualenv-3.0.0.dist-info/RECORD
