Metadata-Version: 2.1
Name: custom-virtualenv
Version: 3.0.0
Summary: Custom Virtual Environment Manager is a utility that allows you to create virtual environments with packages of your choice, based on the Python packages installed globally on your system.
Home-page: https://github.com/afrhan-repo/custom-virtualenv
Author: afrhan-repo
Author-email: afrhanhossain11@gmail.com
Classifier: Programming Language :: Python :: 3
Classifier: License :: OSI Approved :: MIT License
Classifier: Operating System :: POSIX :: Linux
Classifier: Operating System :: MacOS
Requires-Python: >=3.7
License-File: LICENSE
Requires-Dist: InquirerPy
Requires-Dist: pipdeptree
Requires-Dist: virtualenv
